{
  "light-passing": true,
  "model": "custom",
  "model-primitives": {
    "aabbs": [
      [
        0,
        0.45,
        0.45,
        0.45,
        0.1,
        0.1,
        "wire_iron"
      ],
      [
        0.55,
        0.45,
        0.45,
        0.45,
        0.1,
        0.1,
        "wire_iron"
      ],
      [
        0.45,
        0,
        0.45,
        0.1,
        0.45,
        0.1,
        "wire_iron"
      ],
      [
        0.45,
        0.55,
        0.45,
        0.1,
        0.45,
        0.1,
        "wire_iron"
      ],
      [
        0.45,
        0.45,
        0,
        0.1,
        0.1,
        0.45,
        "wire_iron"
      ],
      [
        0.42,
        0.42,
        0.42,
        0.16,
        0.16,
        0.16,
        "wire_iron"
      ],
      [
        0.42,
        0.42,
        0.42,
        0.16,
        0.16,
        0.16,
        "wire_iron"
      ]
    ]
  },
  "hidden": true,
  "picking-item": "electrical_age_lite:wire_iron",
  "script-name": "wire_logic"
}